crash_after/__init__.py
crash_after/crash_after.py
crash_after-0.1.0.dist-info/LICENSE
crash_after-0.1.0.dist-info/METADATA
crash_after-0.1.0.dist-info/WHEEL
crash_after-0.1.0.dist-info/top_level.txt
crash_after-0.1.0.dist-info/RECORD
